cubicweb_workorder/__init__.py
cubicweb_workorder/__pkginfo__.py
cubicweb_workorder/entities.py
cubicweb_workorder/hooks.py
cubicweb_workorder/schema.py
cubicweb_workorder/sobjects.py
cubicweb_workorder/views.py
cubicweb_workorder/i18n/en.po
cubicweb_workorder/i18n/fr.po
cubicweb_workorder/migration/0.11.0_Any.py
cubicweb_workorder/migration/0.13.0_Any.py
cubicweb_workorder/migration/0.6.0_Any.py
cubicweb_workorder/migration/0.6.2_Any.py
cubicweb_workorder/migration/0.9.0_Any.py
cubicweb_workorder/migration/0.9.1_Any.py
cubicweb_workorder/migration/postcreate.py
cubicweb_workorder-1.1.1.dist-info/METADATA
cubicweb_workorder-1.1.1.dist-info/WHEEL
cubicweb_workorder-1.1.1.dist-info/entry_points.txt
cubicweb_workorder-1.1.1.dist-info/top_level.txt
cubicweb_workorder-1.1.1.dist-info/RECORD
